MANIFEST.in
README.rst
UNLICENSE
setup.py
bin/benchmark_pydy_code_gen.py
pydy_code_gen/__init__.py
pydy_code_gen/code.py
pydy_code_gen/templates.py
pydy_code_gen.egg-info/PKG-INFO
pydy_code_gen.egg-info/SOURCES.txt
pydy_code_gen.egg-info/dependency_links.txt
pydy_code_gen.egg-info/requires.txt
pydy_code_gen.egg-info/top_level.txt
pydy_code_gen/tests/__init__.py
pydy_code_gen/tests/models.py
pydy_code_gen/tests/test_code.py
pydy_code_gen/tests/whipple.py