Metadata-Version: 1.1
Name: pydy-code-gen
Version: 0.1.0
Summary: Code generation for multibody dynamic systems.
Home-page: https://github.com/PythonDynamics/pydy-code-gen/
Author: Jason K. Moore
Author-email: moorepants@gmail.com
License: UNLICENSE
Keywords: dynamics multibody simulation code generation
Platform: UNKNOWN
Classifier: Development Status :: 3 - Alpha
Classifier: Intended Audience :: Science/Research
Classifier: Operating System :: OS Independent
Classifier: Programming Language :: Python :: 2.7
Classifier: Topic :: Scientific/Engineering :: Physics
